controlgym/__init__.py
controlgym/controllers/__init__.py
controlgym/controllers/h2hinf.py
controlgym/controllers/lqg.py
controlgym/controllers/lqr.py
controlgym/controllers/ppo.py
controlgym/controllers/zero.py
controlgym/envs/__init__.py
controlgym/envs/allen_cahn.py
controlgym/envs/burgers.py
controlgym/envs/cahn_hilliard.py
controlgym/envs/convection_diffusion_reaction.py
controlgym/envs/fisher.py
controlgym/envs/ginzburg_landau.py
controlgym/envs/korteweg_de_vries.py
controlgym/envs/kuramoto_sivashinsky.py
controlgym/envs/linear_control.py
controlgym/envs/linear_control_src/__init__.py
controlgym/envs/linear_control_src/ac1.mat
controlgym/envs/linear_control_src/ac10.mat
controlgym/envs/linear_control_src/ac2.mat
controlgym/envs/linear_control_src/ac3.mat
controlgym/envs/linear_control_src/ac4.mat
controlgym/envs/linear_control_src/ac5.mat
controlgym/envs/linear_control_src/ac6.mat
controlgym/envs/linear_control_src/ac7.mat
controlgym/envs/linear_control_src/ac8.mat
controlgym/envs/linear_control_src/ac9.mat
controlgym/envs/linear_control_src/bdt1.mat
controlgym/envs/linear_control_src/bdt2.mat
controlgym/envs/linear_control_src/cbm.mat
controlgym/envs/linear_control_src/cdp.mat
controlgym/envs/linear_control_src/cm1.mat
controlgym/envs/linear_control_src/cm2.mat
controlgym/envs/linear_control_src/cm3.mat
controlgym/envs/linear_control_src/cm4.mat
controlgym/envs/linear_control_src/cm5.mat
controlgym/envs/linear_control_src/dis1.mat
controlgym/envs/linear_control_src/dis2.mat
controlgym/envs/linear_control_src/dlr.mat
controlgym/envs/linear_control_src/he1.mat
controlgym/envs/linear_control_src/he2.mat
controlgym/envs/linear_control_src/he3.mat
controlgym/envs/linear_control_src/he4.mat
controlgym/envs/linear_control_src/he5.mat
controlgym/envs/linear_control_src/he6.mat
controlgym/envs/linear_control_src/iss.mat
controlgym/envs/linear_control_src/je1.mat
controlgym/envs/linear_control_src/je2.mat
controlgym/envs/linear_control_src/lah.mat
controlgym-1.0.0.dist-info/LICENSE
controlgym-1.0.0.dist-info/METADATA
controlgym-1.0.0.dist-info/WHEEL
controlgym-1.0.0.dist-info/RECORD
