Metadata-Version: 2.1
Name: controlgym
Version: 1.0.0
Summary: large-scale safety-critical control benchmarks for reinforcement learning algorithms
License: MIT
Author: Xiangyuan Zhang
Author-email: xz7@illinois.edu
Requires-Python: >=3.10,<4.0
Classifier: License :: OSI Approved :: MIT License
Classifier: Programming Language :: Python :: 3
Classifier: Programming Language :: Python :: 3.10
Classifier: Programming Language :: Python :: 3.11
Classifier: Programming Language :: Python :: 3.12
Requires-Dist: gymnasium (==0.29.1)
Requires-Dist: matplotlib (>=3.7.1,<4.0.0)
Requires-Dist: numpy (>=1.23.5,<2.0.0)
Requires-Dist: scipy (>=1.11.1,<2.0.0)
Requires-Dist: torch (>=2.0.1,<3.0.0)
